filememo/__init__.py
filememo/_constants.py
filememo/_deco.py
filememo/_dir_for_func.py
filememo/_indirect_caller.py
filememo-0.3.4.dist-info/LICENSE
filememo-0.3.4.dist-info/METADATA
filememo-0.3.4.dist-info/WHEEL
filememo-0.3.4.dist-info/top_level.txt
filememo-0.3.4.dist-info/RECORD
