Metadata-Version: 2.1
Name: filememo
Version: 0.3.4
Summary: File-based memoization decorator. Stores the results of expensive function calls and returns the cached result when the same inputs occur again.
Home-page: https://github.com/rtmigo/filememo_py#readme
Author: Artёm IG
Author-email: ortemeo@gmail.com
License: MIT
Keywords: python,package,memoize,memoization,cache,function,file,persistent,method,memoize-decorator,memoization-library,permanent,pickle
Platform: UNKNOWN
Classifier: Development Status :: 4 - Beta
Classifier: License :: OSI Approved :: MIT License
Classifier: Programming Language :: Python :: 3.8
Classifier: Programming Language :: Python :: 3.9
Classifier: Programming Language :: Python :: 3.10
Classifier: Operating System :: POSIX
Classifier: Operating System :: Microsoft :: Windows
Requires-Python: >=3.8
License-File: LICENSE
Requires-Dist: pickledir (>=0.3.5)
